business/__init__.py
business/__main__.py
business/calculator.py
business_calculate-0.1.0.dist-info/METADATA
business_calculate-0.1.0.dist-info/WHEEL
business_calculate-0.1.0.dist-info/top_level.txt
business_calculate-0.1.0.dist-info/RECORD
