Metadata-Version: 2.1
Name: business-calculate
Version: 0.1.0
Summary: Расчёты метрик
Author-email: Matvey Perminov <mectu@mail.ru>
License: MIT
Requires-Python: >=3.12
